visepoint/__init__.py
visepoint/requirements.txt
visepoint/connection/__init__.py
visepoint/connection/models.py
visepoint/connection/users.py
visepoint/connection/data/__init__.py
visepoint/connection/data/resources.py
visepoint/errors/__init__.py
visepoint/errors/err.py
visepoint-0.12.86.dist-info/LICENSE
visepoint-0.12.86.dist-info/METADATA
visepoint-0.12.86.dist-info/WHEEL
visepoint-0.12.86.dist-info/top_level.txt
visepoint-0.12.86.dist-info/RECORD
