Metadata-Version: 2.1
Name: visepoint
Version: 0.12.86
Summary: "This Python module is for interacting with the visepoint API!"
Home-page: https://github.com/visepoint/visepoint-py
Author: "kitsu#0006"
Author-email: "kitsu@visepoint.net"
Requires-Python: >=3.9
License-File: LICENSE
